[
  {
    "CustomerID": 1,
    "CustomerNumber": "K001",
    "CompanyName": "Acme AB",
    "OrganizationNumber": "556123-4567",
    "Phone": "08-123 45 67",
    "Email": "anna@acme.se",
    "Address": "Storgatan 12",
    "PostalCode": "111 22",
    "City": "Stockholm",
    "Country": "Sverige",
    "InvoiceAddress": {
      "Address": "Box 123",
      "PostalCode": "111 22",
      "City": "Stockholm"
    },
    "PaymentTerms": 30,
    "VATNumber": "SE556123456701",
    "Status": "active",
    "CreatedDate": "2024-01-01",
    "Notes": "Stor kund med regelbundna uppdrag"
  },
  {
    "CustomerID": 2,
    "CustomerNumber": "K002",
    "CompanyName": "Byggfirma Nord",
    "OrganizationNumber": "556234-5678",
    "Phone": "08-234 56 78",
    "Email": "bengt@byggfirmanord.se",
    "Address": "Industrivägen 45",
    "PostalCode": "123 45",
    "City": "Göteborg",
    "Country": "Sverige",
    "InvoiceAddress": {
      "Address": "Industrivägen 45",
      "PostalCode": "123 45",
      "City": "Göteborg"
    },
    "PaymentTerms": 30,
    "VATNumber": "SE556234567801",
    "Status": "active",
    "CreatedDate": "2024-01-15",
    "Notes": "Specialiserade på ventilationssystem"
  },
  {
    "CustomerID": 3,
    "CustomerNumber": "K003",
    "CompanyName": "City Fastigheter",
    "OrganizationNumber": "556345-6789",
    "Phone": "08-345 67 89",
    "Email": "cecilia@cityfastigheter.se",
    "Address": "Fastighetsvägen 78",
    "PostalCode": "234 56",
    "City": "Malmö",
    "Country": "Sverige",
    "InvoiceAddress": {
      "Address": "Box 456",
      "PostalCode": "234 56",
      "City": "Malmö"
    },
    "PaymentTerms": 45,
    "VATNumber": "SE556345678901",
    "Status": "active",
    "CreatedDate": "2024-02-01",
    "Notes": "Fastighetsförvaltare med många objekt"
  },
  {
    "CustomerID": 4,
    "CustomerNumber": "K004",
    "CompanyName": "Tech Solutions AB",
    "OrganizationNumber": "556456-7890",
    "Phone": "08-456 78 90",
    "Email": "david@techsolutions.se",
    "Address": "Teknikgatan 23",
    "PostalCode": "345 67",
    "City": "Uppsala",
    "Country": "Sverige",
    "InvoiceAddress": {
      "Address": "Teknikgatan 23",
      "PostalCode": "345 67",
      "City": "Uppsala"
    },
    "PaymentTerms": 30,
    "VATNumber": "SE556456789001",
    "Status": "active",
    "CreatedDate": "2024-02-15",
    "Notes": "IT-företag med moderna lokaler"
  },
  {
    "CustomerID": 5,
    "CustomerNumber": "K005",
    "CompanyName": "Green Energy Corp",
    "OrganizationNumber": "556567-8901",
    "Phone": "08-567 89 01",
    "Email": "eva@greenenergy.se",
    "Address": "Miljövägen 56",
    "PostalCode": "456 78",
    "City": "Linköping",
    "Country": "Sverige",
    "InvoiceAddress": {
      "Address": "Box 789",
      "PostalCode": "456 78",
      "City": "Linköping"
    },
    "PaymentTerms": 30,
    "VATNumber": "SE556567890101",
    "Status": "active",
    "CreatedDate": "2024-03-01",
    "Notes": "Fokus på hållbara energilösningar"
  },
  {
    "CustomerID": 6,
    "CustomerNumber": "K006",
    "CompanyName": "Nordic Manufacturing",
    "OrganizationNumber": "556678-9012",
    "Phone": "08-678 90 12",
    "Email": "fredrik@nordicmanufacturing.se",
    "Address": "Fabriksgatan 89",
    "PostalCode": "567 89",
    "City": "Västerås",
    "Country": "Sverige",
    "InvoiceAddress": {
      "Address": "Fabriksgatan 89",
      "PostalCode": "567 89",
      "City": "Västerås"
    },
    "PaymentTerms": 30,
    "VATNumber": "SE556678901201",
    "Status": "inactive",
    "CreatedDate": "2023-12-01",
    "Notes": "Tillfälligt inaktiv - omstrukturering"
  },
  {
    "CustomerID": 7,
    "CustomerNumber": "K007",
    "CompanyName": "Scandia Logistics",
    "OrganizationNumber": "556789-0123",
    "Phone": "08-789 01 23",
    "Email": "gustav@scandialogistics.se",
    "Address": "Transportgatan 34",
    "PostalCode": "678 90",
    "City": "Örebro",
    "Country": "Sverige",
    "InvoiceAddress": {
      "Address": "Box 890",
      "PostalCode": "678 90",
      "City": "Örebro"
    },
    "PaymentTerms": 30,
    "VATNumber": "SE556789012301",
    "Status": "active",
    "CreatedDate": "2024-03-15",
    "Notes": "Transportföretag med rikstäckande verksamhet"
  },
  {
    "CustomerID": 8,
    "CustomerNumber": "K008",
    "CompanyName": "Retail Solutions AB",
    "OrganizationNumber": "556890-1234",
    "Phone": "08-890 12 34",
    "Email": "helena@retailsolutions.se",
    "Address": "Handelsgatan 67",
    "PostalCode": "789 01",
    "City": "Jönköping",
    "Country": "Sverige",
    "InvoiceAddress": {
      "Address": "Handelsgatan 67",
      "PostalCode": "789 01",
      "City": "Jönköping"
    },
    "PaymentTerms": 30,
    "VATNumber": "SE556890123401",
    "Status": "active",
    "CreatedDate": "2024-04-01",
    "Notes": "Butiksinredningar och kassasystem"
  },
  {
    "CustomerID": 9,
    "CustomerNumber": "K009",
    "OrganizationNumber": "556901-2345",
    "Phone": "08-901 23 45",
    "Email": "ingvar@marineservices.se",
    "Address": "Hamnvägen 12",
    "PostalCode": "890 12",
    "City": "Helsingborg",
    "Country": "Sverige",
    "InvoiceAddress": {
      "Address": "Box 123",
      "PostalCode": "890 12",
      "City": "Helsingborg"
    },
    "PaymentTerms": 45,
    "VATNumber": "SE556901234501",
    "Status": "active",
    "CreatedDate": "2024-04-15",
    "Notes": "Marin service och båtreparationer"
  },
  {
    "CustomerID": 10,
    "CustomerNumber": "K010",
    "CompanyName": "Food & Beverage Co",
    "OrganizationNumber": "556012-3456",
    "Phone": "08-012 34 56",
    "Email": "johanna@foodbeverage.se",
    "Address": "Restaurangvägen 45",
    "PostalCode": "901 23",
    "City": "Karlstad",
    "Country": "Sverige",
    "InvoiceAddress": {
      "Address": "Restaurangvägen 45",
      "PostalCode": "901 23",
      "City": "Karlstad"
    },
    "PaymentTerms": 30,
    "VATNumber": "SE556012345601",
    "Status": "active",
    "CreatedDate": "2024-05-01",
    "Notes": "Restaurangkedja med flera enheter"
  },
  {
    "CustomerID": 11,
    "CustomerNumber": "K011",
    "CompanyName": "Healthcare Solutions",
    "OrganizationNumber": "556123-4567",
    "Phone": "08-123 45 67",
    "Email": "karl@healthcaresolutions.se",
    "Address": "Vårdgatan 78",
    "PostalCode": "012 34",
    "City": "Sundsvall",
    "Country": "Sverige",
    "InvoiceAddress": {
      "Address": "Box 456",
      "PostalCode": "012 34",
      "City": "Sundsvall"
    },
    "PaymentTerms": 30,
    "VATNumber": "SE556123456701",
    "Status": "active",
    "CreatedDate": "2024-05-15",
    "Notes": "Medicinteknisk utrustning"
  },
  {
    "CustomerID": 12,
    "CustomerNumber": "K012",
    "CompanyName": "Education First AB",
    "OrganizationNumber": "556234-5678",
    "Phone": "08-234 56 78",
    "Email": "lisa@educationfirst.se",
    "Address": "Skolvägen 23",
    "PostalCode": "123 45",
    "City": "Umeå",
    "Country": "Sverige",
    "InvoiceAddress": {
      "Address": "Skolvägen 23",
      "PostalCode": "123 45",
      "City": "Umeå"
    },
    "PaymentTerms": 30,
    "VATNumber": "SE556234567801",
    "Status": "active",
    "CreatedDate": "2024-06-01",
    "Notes": "Utbildningsmaterial och kurser"
  },
  {
    "CustomerID": 13,
    "CustomerNumber": "K013",
    "CompanyName": "Sports & Recreation",
    "OrganizationNumber": "556345-6789",
    "Phone": "08-345 67 89",
    "Email": "magnus@sportsrecreation.se",
    "Address": "Idrottsgatan 56",
    "PostalCode": "234 56",
    "City": "Luleå",
    "Country": "Sverige",
    "InvoiceAddress": {
      "Address": "Box 789",
      "PostalCode": "234 56",
      "City": "Luleå"
    },
    "PaymentTerms": 30,
    "VATNumber": "SE556345678901",
    "Status": "active",
    "CreatedDate": "2024-06-15",
    "Notes": "Sportutrustning och anläggningar"
  },
  {
    "CustomerID": 14,
    "CustomerNumber": "K014",
    "CompanyName": "Security Systems AB",
    "OrganizationNumber": "556456-7890",
    "Phone": "08-456 78 90",
    "Email": "nina@securitysystems.se",
    "Address": "Säkerhetsgatan 89",
    "PostalCode": "345 67",
    "City": "Kiruna",
    "Country": "Sverige",
    "InvoiceAddress": {
      "Address": "Säkerhetsgatan 89",
      "PostalCode": "345 67",
      "City": "Kiruna"
    },
    "PaymentTerms": 30,
    "VATNumber": "SE556456789001",
    "Status": "active",
    "CreatedDate": "2024-07-01",
    "Notes": "Säkerhetslösningar och övervakning"
  },
  {
    "CustomerID": 15,
    "CustomerNumber": "K015",
    "CompanyName": "Textile Industries",
    "OrganizationNumber": "556567-8901",
    "Phone": "08-567 89 01",
    "Email": "olof@textileindustries.se",
    "Address": "Textilvägen 12",
    "PostalCode": "456 78",
    "City": "Borås",
    "Country": "Sverige",
    "InvoiceAddress": {
      "Address": "Box 012",
      "PostalCode": "456 78",
      "City": "Borås"
    },
    "PaymentTerms": 45,
    "VATNumber": "SE556567890101",
    "Status": "inactive",
    "CreatedDate": "2023-11-01",
    "Notes": "Tillfälligt stoppad produktion"
  },
  {
    "CustomerID": 16,
    "CustomerNumber": "K016",
    "CompanyName": "Automotive Parts",
    "OrganizationNumber": "556678-9012",
    "Phone": "08-678 90 12",
    "Email": "petra@automotiveparts.se",
    "Address": "Bildelarsgatan 34",
    "PostalCode": "567 89",
    "City": "Trollhättan",
    "Country": "Sverige",
    "InvoiceAddress": {
      "Address": "Bildelarsgatan 34",
      "PostalCode": "567 89",
      "City": "Trollhättan"
    },
    "PaymentTerms": 30,
    "VATNumber": "SE556678901201",
    "Status": "active",
    "CreatedDate": "2024-07-15",
    "Notes": "Reservdelar och tillbehör"
  },
  {
    "CustomerID": 17,
    "CustomerNumber": "K017",
    "CompanyName": "Digital Marketing AB",
    "OrganizationNumber": "556789-0123",
    "Phone": "08-789 01 23",
    "Email": "quintus@digitalmarketing.se",
    "Address": "Reklämgatan 67",
    "PostalCode": "678 90",
    "City": "Eskilstuna",
    "Country": "Sverige",
    "InvoiceAddress": {
      "Address": "Box 345",
      "PostalCode": "678 90",
      "City": "Eskilstuna"
    },
    "PaymentTerms": 30,
    "VATNumber": "SE556789012301",
    "Status": "active",
    "CreatedDate": "2024-08-01",
    "Notes": "Digitala marknadsföringslösningar"
  },
  {
    "CustomerID": 18,
    "CustomerNumber": "K018",
    "CompanyName": "Renewable Energy Corp",
    "OrganizationNumber": "556890-1234",
    "Phone": "08-890 12 34",
    "Email": "rita@renewableenergy.se",
    "Address": "Solenergivägen 90",
    "PostalCode": "789 01",
    "City": "Sandviken",
    "Country": "Sverige",
    "InvoiceAddress": {
      "Address": "Solenergivägen 90",
      "PostalCode": "789 01",
      "City": "Sandviken"
    },
    "PaymentTerms": 30,
    "VATNumber": "SE556890123401",
    "Status": "active",
    "CreatedDate": "2024-08-15",
    "Notes": "Sol- och vindkraftslösningar"
  },
  {
    "CustomerID": 19,
    "CustomerNumber": "K019",
    "CompanyName": "Financial Services AB",
    "OrganizationNumber": "556901-2345",
    "Phone": "08-901 23 45",
    "Email": "sven@financialservices.se",
    "Address": "Bankgatan 23",
    "PostalCode": "890 12",
    "City": "Falun",
    "Country": "Sverige",
    "InvoiceAddress": {
      "Address": "Box 678",
      "PostalCode": "890 12",
      "City": "Falun"
    },
    "PaymentTerms": 30,
    "VATNumber": "SE556901234501",
    "Status": "active",
    "CreatedDate": "2024-09-01",
    "Notes": "Ekonomisk rådgivning och tjänster"
  },
  {
    "CustomerID": 20,
    "CustomerNumber": "K020",
    "CompanyName": "Pharmaceutical Solutions",
    "OrganizationNumber": "556012-3456",
    "Phone": "08-012 34 56",
    "Email": "tina@pharmasolutions.se",
    "Address": "Apoteksgatan 45",
    "PostalCode": "901 23",
    "City": "Gävle",
    "Country": "Sverige",
    "InvoiceAddress": {
      "Address": "Box 901",
      "PostalCode": "901 23",
      "City": "Gävle"
    },
    "PaymentTerms": 45,
    "VATNumber": "SE556012345601",
    "Status": "active",
    "CreatedDate": "2024-09-15",
    "Notes": "Läkemedel och medicinska produkter"
  },
  {
    "CustomerID": 21,
    "CustomerNumber": "K021",
    "CompanyName": "Construction Materials",
    "OrganizationNumber": "556123-4567",
    "Phone": "08-123 45 67",
    "Email": "urban@constructionmaterials.se",
    "Address": "Byggmaterialgatan 78",
    "PostalCode": "012 34",
    "City": "Borlänge",
    "Country": "Sverige",
    "InvoiceAddress": {
      "Address": "Byggmaterialgatan 78",
      "PostalCode": "012 34",
      "City": "Borlänge"
    },
    "PaymentTerms": 30,
    "VATNumber": "SE556123456701",
    "Status": "active",
    "CreatedDate": "2024-10-01",
    "Notes": "Byggmaterial och verktyg"
  },
  {
    "CustomerID": 22,
    "CustomerNumber": "K022",
    "CompanyName": "Event Management AB",
    "OrganizationNumber": "556234-5678",
    "Phone": "08-234 56 78",
    "Email": "vera@eventmanagement.se",
    "Address": "Eventgatan 12",
    "PostalCode": "123 45",
    "City": "Hudiksvall",
    "Country": "Sverige",
    "InvoiceAddress": {
      "Address": "Box 234",
      "PostalCode": "123 45",
      "City": "Hudiksvall"
    },
    "PaymentTerms": 30,
    "VATNumber": "SE556234567801",
    "Status": "active",
    "CreatedDate": "2024-10-15",
    "Notes": "Eventplanering och koordinering"
  },
  {
    "CustomerID": 23,
    "CustomerNumber": "K023",
    "CompanyName": "Waste Management Corp",
    "OrganizationNumber": "556345-6789",
    "Phone": "08-345 67 89",
    "Email": "wilhelm@wastemanagement.se",
    "Address": "Återvinningsgatan 34",
    "PostalCode": "234 56",
    "City": "Söderhamn",
    "Country": "Sverige",
    "InvoiceAddress": {
      "Address": "Box 567",
      "PostalCode": "234 56",
      "City": "Söderhamn"
    },
    "PaymentTerms": 30,
    "VATNumber": "SE556345678901",
    "Status": "active",
    "CreatedDate": "2024-11-01",
    "Notes": "Avfallshantering och återvinning"
  },
  {
    "CustomerID": 24,
    "CustomerNumber": "K024",
    "CompanyName": "Insurance Brokers AB",
    "OrganizationNumber": "556456-7890",
    "Phone": "08-456 78 90",
    "Email": "ximena@insurancebrokers.se",
    "Address": "Försäkringsgatan 56",
    "PostalCode": "345 67",
    "City": "Bollnäs",
    "Country": "Sverige",
    "InvoiceAddress": {
      "Address": "Försäkringsgatan 56",
      "PostalCode": "345 67",
      "City": "Bollnäs"
    },
    "PaymentTerms": 30,
    "VATNumber": "SE556456789001",
    "Status": "active",
    "CreatedDate": "2024-11-15",
    "Notes": "Försäkringsmäklare och riskanalys"
  },
  {
    "CustomerID": 25,
    "CustomerNumber": "K025",
    "CompanyName": "Travel Services",
    "OrganizationNumber": "556567-8901",
    "Phone": "08-567 89 01",
    "Email": "yngve@travelservices.se",
    "Address": "Resebyrågatan 78",
    "PostalCode": "456 78",
    "City": "Ljusdal",
    "Country": "Sverige",
    "InvoiceAddress": {
      "Address": "Box 890",
      "PostalCode": "456 78",
      "City": "Ljusdal"
    },
    "PaymentTerms": 30,
    "VATNumber": "SE556567890101",
    "Status": "inactive",
    "CreatedDate": "2023-10-01",
    "Notes": "Pausad verksamhet under pandemin"
  },
  {
    "CustomerID": 26,
    "CustomerNumber": "K026",
    "CompanyName": "Legal Advisors AB",
    "OrganizationNumber": "556678-9012",
    "Phone": "08-678 90 12",
    "Email": "zelda@legaladvisors.se",
    "Address": "Juristgatan 90",
    "PostalCode": "567 89",
    "City": "Ovanåker",
    "Country": "Sverige",
    "InvoiceAddress": {
      "Address": "Juristgatan 90",
      "PostalCode": "567 89",
      "City": "Ovanåker"
    },
    "PaymentTerms": 30,
    "VATNumber": "SE556678901201",
    "Status": "active",
    "CreatedDate": "2024-12-01",
    "Notes": "Juridisk rådgivning och konsultation"
  },
  {
    "CustomerID": 27,
    "CustomerNumber": "K027",
    "CompanyName": "Media Production Corp",
    "OrganizationNumber": "556789-0123",
    "Phone": "08-789 01 23",
    "Email": "ake@mediaproduction.se",
    "Address": "Mediagatan 12",
    "PostalCode": "678 90",
    "City": "Ockelbo",
    "Country": "Sverige",
    "InvoiceAddress": {
      "Address": "Box 123",
      "PostalCode": "678 90",
      "City": "Ockelbo"
    },
    "PaymentTerms": 30,
    "VATNumber": "SE556789012301",
    "Status": "active",
    "CreatedDate": "2024-12-15",
    "Notes": "Film- och videoproduktion"
  },
  {
    "CustomerID": 28,
    "CustomerNumber": "K028",
    "CompanyName": "Agricultural Solutions",
    "OrganizationNumber": "556890-1234",
    "Phone": "08-890 12 34",
    "Email": "arla@agriculturalsolutions.se",
    "Address": "Jordbruksgatan 34",
    "PostalCode": "789 01",
    "City": "Hofors",
    "Country": "Sverige",
    "InvoiceAddress": {
      "Address": "Jordbruksgatan 34",
      "PostalCode": "789 01",
      "City": "Hofors"
    },
    "PaymentTerms": 45,
    "VATNumber": "SE556890123401",
    "Status": "active",
    "CreatedDate": "2025-01-01",
    "Notes": "Jordbruksmaskiner och utrustning"
  },
  {
    "CustomerID": 29,
    "CustomerNumber": "K029",
    "CompanyName": "Interior Design AB",
    "OrganizationNumber": "556901-2345",
    "Phone": "08-901 23 45",
    "Email": "osten@interiordesign.se",
    "Address": "Designgatan 56",
    "PostalCode": "890 12",
    "City": "Sandviken",
    "Country": "Sverige",
    "InvoiceAddress": {
      "Address": "Box 456",
      "PostalCode": "890 12",
      "City": "Sandviken"
    },
    "PaymentTerms": 30,
    "VATNumber": "SE556901234501",
    "Status": "active",
    "CreatedDate": "2025-01-15",
    "Notes": "Inredningsdesign och konsultation"
  },
  {
    "CustomerID": 30,
    "CustomerNumber": "K030",
    "CompanyName": "Climate Solutions Corp",
    "OrganizationNumber": "556012-3456",
    "Phone": "08-012 34 56",
    "Email": "asa@climatesolutions.se",
    "Address": "Klimatgatan 78",
    "PostalCode": "901 23",
    "City": "Avesta",
    "Country": "Sverige",
    "InvoiceAddress": {
      "Address": "Klimatgatan 78",
      "PostalCode": "901 23",
      "City": "Avesta"
    },
    "PaymentTerms": 30,
    "VATNumber": "SE556012345601",
    "Status": "active",
    "CreatedDate": "2025-02-01",
    "Notes": "Klimatlösningar och miljökonsultation"
  }
]
